uvotredux/__init__.py
uvotredux/cli.py
uvotredux/paths.py
uvotredux/run.py
uvotredux/download/__init__.py
uvotredux/download/data.py
uvotredux/download/regions.py
uvotredux/download/run.py
uvotredux/utils/__init__.py
uvotredux/utils/name.py
uvotredux/utils/paths.py
uvotredux/utils/skyportal.py
uvotredux/utils/time.py
uvotredux/utils/tns.py
uvotredux/uvot/__init__.py
uvotredux/uvot/filters.py
uvotredux/uvot/iterate.py
uvotredux/uvot/parse.py
uvotredux/uvot/reduce.py
uvotredux/xrt/iterate.py
uvotredux/xrt/reduce.py
uvotredux-0.3.1.dist-info/licenses/LICENSE
uvotredux-0.3.1.dist-info/METADATA
uvotredux-0.3.1.dist-info/WHEEL
uvotredux-0.3.1.dist-info/entry_points.txt
uvotredux-0.3.1.dist-info/top_level.txt
uvotredux-0.3.1.dist-info/RECORD
