Metadata-Version: 2.4
Name: uvotredux
Version: 0.3.1
Summary: Python wrapper to reduce Swift UVOT data
Author-email: Robert Stein <rdstein@caltech.edu>
License: MIT
Project-URL: Homepage, https://github.com/robertdstein/uvotredux
Classifier: Programming Language :: Python :: 3
Classifier: Programming Language :: Python :: 3.10
Classifier: Programming Language :: Python :: 3.11
Classifier: Programming Language :: Python :: 3.12
Classifier: Intended Audience :: Science/Research
Classifier: Intended Audience :: End Users/Desktop
Classifier: Intended Audience :: Developers
Classifier: Natural Language :: English
Classifier: Topic :: Scientific/Engineering
Classifier: Topic :: Scientific/Engineering :: Astronomy
Classifier: Topic :: Scientific/Engineering :: Physics
Classifier: Operating System :: POSIX
Classifier: Operating System :: Unix
Classifier: Operating System :: MacOS
Requires-Python: >=3.10
License-File: LICENSE
Requires-Dist: pathlib
Requires-Dist: astropy>=6.0.0
Requires-Dist: pandas
Requires-Dist: swifttools>=3.0.0
Provides-Extra: dev
Requires-Dist: black==25.1.0; extra == "dev"
Requires-Dist: isort==6.0.1; extra == "dev"
Requires-Dist: pylint==3.3.7; extra == "dev"
Requires-Dist: coveralls; extra == "dev"
Requires-Dist: pre-commit; extra == "dev"
Dynamic: license-file
